{"note":"This file is an internal implementation detail to speed up HTML report generation. Its format can change at any time. You might be looking for the JSON report: https://coverage.rtfd.io/cmd.html#cmd-json","format":5,"version":"7.9.1","globals":"22744a151ae3bb2f9293bbbb35e529b4","files":{"z_145eef247bfb46b6___init___py":{"hash":"e6baa73cda2916dad605215f937a92e1","index":{"url":"z_145eef247bfb46b6___init___py.html","file":"src\\__init__.py","description":"","nums":{"precision":0,"n_files":1,"n_statements":0,"n_excluded":0,"n_missing":0,"n_branches":0,"n_partial_branches":0,"n_missing_branches":0}}},"z_145eef247bfb46b6_masks_py":{"hash":"56e982e820a93943a03665fa48bf6d64","index":{"url":"z_145eef247bfb46b6_masks_py.html","file":"src\\masks.py","description":"","nums":{"precision":0,"n_files":1,"n_statements":6,"n_excluded":0,"n_missing":0,"n_branches":0,"n_partial_branches":0,"n_missing_branches":0}}},"z_145eef247bfb46b6_processing_py":{"hash":"fe00f4c822b07227b0f6f81e7177db79","index":{"url":"z_145eef247bfb46b6_processing_py.html","file":"src\\processing.py","description":"","nums":{"precision":0,"n_files":1,"n_statements":5,"n_excluded":0,"n_missing":0,"n_branches":0,"n_partial_branches":0,"n_missing_branches":0}}},"z_145eef247bfb46b6_widget_py":{"hash":"e328f156e1623d612a63a24a521a9a86","index":{"url":"z_145eef247bfb46b6_widget_py.html","file":"src\\widget.py","description":"","nums":{"precision":0,"n_files":1,"n_statements":13,"n_excluded":0,"n_missing":0,"n_branches":0,"n_partial_branches":0,"n_missing_branches":0}}},"z_145eef247bfb46b6_generators_py":{"hash":"464e5390dc493d742e18eec9e1812c35","index":{"url":"z_145eef247bfb46b6_generators_py.html","file":"src\\generators.py","description":"","nums":{"precision":0,"n_files":1,"n_statements":13,"n_excluded":0,"n_missing":0,"n_branches":0,"n_partial_branches":0,"n_missing_branches":0}}},"z_145eef247bfb46b6_transaction_data_py":{"hash":"2f5f8214f7f07d32ac8a2d1808e3ad5f","index":{"url":"z_145eef247bfb46b6_transaction_data_py.html","file":"src\\transaction_data.py","description":"","nums":{"precision":0,"n_files":1,"n_statements":1,"n_excluded":0,"n_missing":0,"n_branches":0,"n_partial_branches":0,"n_missing_branches":0}}}}}